MANIFEST.in
README.rst
setup.py
fuzzyhashlib/__init__.py
fuzzyhashlib/common.py
fuzzyhashlib/libssdeep_wrapper.py
fuzzyhashlib/sdbf_class.py
fuzzyhashlib/sdhash_wrapper.py
fuzzyhashlib/tlsh_wrapper.py
fuzzyhashlib/version.py
fuzzyhashlib.egg-info/PKG-INFO
fuzzyhashlib.egg-info/SOURCES.txt
fuzzyhashlib.egg-info/dependency_links.txt
fuzzyhashlib.egg-info/not-zip-safe
fuzzyhashlib.egg-info/top_level.txt
fuzzyhashlib/libs/linux/x86_32/_sdbf_class.so
fuzzyhashlib/libs/linux/x86_32/libssdeep.so
fuzzyhashlib/libs/linux/x86_32/tlsh.so
fuzzyhashlib/libs/linux/x86_64/_sdbf_class.so
fuzzyhashlib/libs/linux/x86_64/libssdeep.so
fuzzyhashlib/libs/linux/x86_64/tlsh.so