Metadata-Version: 1.1
Name: fuzzyhashlib
Version: 0.0.7
Summary: Hashlib-like wrapper for several fuzzy hash algorithms.
Home-page: https://github.com/sptonkin/fuzzyhashlib
Author: Stephen Tonkin
Author-email: sptonkin@outlook.com
License: Apache Software Licence
Platform: linux
Classifier: Development Status :: 3 - Alpha
Classifier: Intended Audience :: Other Audience
Classifier: License :: OSI Approved :: Apache Software License
Classifier: Operating System :: POSIX :: Linux
Classifier: Programming Language :: Python
Classifier: Programming Language :: Python :: 2.7
Classifier: Programming Language :: Python :: Implementation :: CPython
Classifier: Topic :: Security
Classifier: Topic :: Software Development :: Libraries :: Python Modules
